{
  "dialog_id": "57f27c34-1dff-43fe-adc4-e953c9bf70fd",
  "created_timestamp": "2023-02-13T10:58:16.964575+09:00",
  "archived_timestamp": "2023-02-13T11:16:10.262401+09:00",
  "recommender": {
    "name": "001",
    "questionnaire": {
      "knowledge": 5,
      "enjoyment": 4,
      "recommendation_success": 4,
      "movie_num": 5
    }
  },
  "seeker": {
    "name": "012",
    "questionnaire": {
      "knowledge": 2,
      "enjoyment": 5,
      "recommendation_success": 5,
      "movie_num": 1
    }
  },
  "utterances": [
    {
      "id": "0",
      "speaker": "recommender",
      "text": "こんにちは、初めまして。よろしくお願い致します。",
      "timestamp": "2023-02-13T11:00:11.961740+09:00",
      "internal_states": [],
      "searches": [],
      "checked": []
    },
    {
      "id": "1",
      "speaker": "seeker",
      "text": "こんにちは。宜しくお願いします。",
      "timestamp": "2023-02-13T11:00:26.023769+09:00",
      "internal_states": []
    },
    {
      "id": "2",
      "speaker": "recommender",
      "text": "どんなジャンルの映画がお好きですか？邦画、洋画、など、お好みがあれば教えて下さい。",
      "timestamp": "2023-02-13T11:00:42.521507+09:00",
      "internal_states": [
        {
          "id": "0",
          "text": "邦画、洋画",
          "knowledge": {
            "recommender": "どちらとも言えない",
            "seeker": "あり"
          },
          "interest": {
            "recommender": "どちらとも言えない",
            "seeker": "あり"
          }
        }
      ],
      "searches": [],
      "checked": []
    },
    {
      "id": "3",
      "speaker": "seeker",
      "text": "好みは洋画です。寒い季節に暖まるチョコレートやバレンタインにまつわるお話の映画はありますか。",
      "timestamp": "2023-02-13T11:01:52.938312+09:00",
      "internal_states": [
        {
          "id": "1",
          "text": "洋画",
          "knowledge": {
            "recommender": "あり",
            "seeker": "あり"
          },
          "interest": {
            "recommender": "あり",
            "seeker": "あり"
          }
        },
        {
          "id": "2",
          "text": "寒い季節に暖まるチョコレートやバレンタインにまつわるお話の映画",
          "knowledge": {
            "recommender": "なし",
            "seeker": "不適切"
          },
          "interest": {
            "recommender": "あり",
            "seeker": "不適切"
          }
        }
      ]
    },
    {
      "id": "4",
      "speaker": "recommender",
      "text": "バレンタイン、明日ですもんね。チョコレートのお話といえば、「ショコラ」か、「チャーリーとチョコレート工場」ぐらいしか思い浮かばないのですが、ご覧になられましたか？",
      "timestamp": "2023-02-13T11:02:57.415199+09:00",
      "internal_states": [
        {
          "id": "3",
          "text": "バレンタイン、明日ですもん",
          "knowledge": {
            "recommender": "不適切",
            "seeker": "不適切"
          },
          "interest": {
            "recommender": "不適切",
            "seeker": "不適切"
          }
        },
        {
          "id": "4",
          "text": "チョコレートのお話",
          "knowledge": {
            "recommender": "なし",
            "seeker": "どちらとも言えない"
          },
          "interest": {
            "recommender": "あり",
            "seeker": "あり"
          }
        },
        {
          "id": "5",
          "text": "「ショコラ」",
          "knowledge": {
            "recommender": "なし",
            "seeker": "なし"
          },
          "interest": {
            "recommender": "なし",
            "seeker": "あり"
          }
        },
        {
          "id": "6",
          "text": "「チャーリーとチョコレート工場」",
          "knowledge": {
            "recommender": "なし",
            "seeker": "なし"
          },
          "interest": {
            "recommender": "あり",
            "seeker": "あり"
          }
        }
      ],
      "searches": [
        {
          "timestamp": "2023-02-13T11:02:09.608525+09:00",
          "query": "ショコラ",
          "genres": "",
          "results": "162817"
        }
      ],
      "checked": [
        "162817_title"
      ]
    },
    {
      "id": "5",
      "speaker": "seeker",
      "text": "どちらも観ていません。チョコレート工場のお話をお聞きしたいですね。",
      "timestamp": "2023-02-13T11:03:43.898276+09:00",
      "internal_states": [
        {
          "id": "7",
          "text": "チョコレート工場のお話",
          "knowledge": {
            "recommender": "なし",
            "seeker": "なし"
          },
          "interest": {
            "recommender": "あり",
            "seeker": "あり"
          }
        }
      ]
    },
    {
      "id": "6",
      "speaker": "recommender",
      "text": "チャーリーとチョコレート工場は、2005年のアメリカ映画で、監督ティム・バートンと、主演ジョニー・デップのペアで、コメディとファンタジー要素のある、ほのぼのとした映画です。",
      "timestamp": "2023-02-13T11:04:55.790411+09:00",
      "internal_states": [
        {
          "id": "8",
          "text": "チャーリー",
          "knowledge": {
            "recommender": "なし",
            "seeker": "なし"
          },
          "interest": {
            "recommender": "あり",
            "seeker": "あり"
          }
        },
        {
          "id": "9",
          "text": "チョコレート工場",
          "knowledge": {
            "recommender": "なし",
            "seeker": "なし"
          },
          "interest": {
            "recommender": "あり",
            "seeker": "あり"
          }
        },
        {
          "id": "10",
          "text": "2005年のアメリカ映画",
          "knowledge": {
            "recommender": "なし",
            "seeker": "なし"
          },
          "interest": {
            "recommender": "あり",
            "seeker": "あり"
          }
        },
        {
          "id": "11",
          "text": "監督ティム・バートン",
          "knowledge": {
            "recommender": "どちらとも言えない",
            "seeker": "なし"
          },
          "interest": {
            "recommender": "なし",
            "seeker": "あり"
          }
        },
        {
          "id": "12",
          "text": "主演ジョニー・デップのペアで、コメディとファンタジー要素のある、ほのぼのとした映画",
          "knowledge": {
            "recommender": "なし",
            "seeker": "なし"
          },
          "interest": {
            "recommender": "あり",
            "seeker": "あり"
          }
        }
      ],
      "searches": [
        {
          "timestamp": "2023-02-13T11:03:55.547532+09:00",
          "query": "チョコレート",
          "genres": "",
          "results": "162817,163032,321598,344686,348035,362671,362951,363978"
        }
      ],
      "checked": [
        "321598_title",
        "321598_year",
        "321598_director_name",
        "321598_cast_name-1",
        "321598_genre-0",
        "321598_genre-1"
      ]
    },
    {
      "id": "7",
      "speaker": "seeker",
      "text": "私の好みにあっている気がします。ちょっとストーリーを教えて下さい。",
      "timestamp": "2023-02-13T11:05:50.164012+09:00",
      "internal_states": [
        {
          "id": "13",
          "text": "私の好みにあっている気",
          "knowledge": {
            "recommender": "不適切",
            "seeker": "不適切"
          },
          "interest": {
            "recommender": "不適切",
            "seeker": "不適切"
          }
        },
        {
          "id": "14",
          "text": "ストーリー",
          "knowledge": {
            "recommender": "なし",
            "seeker": "なし"
          },
          "interest": {
            "recommender": "あり",
            "seeker": "あり"
          }
        }
      ]
    },
    {
      "id": "8",
      "speaker": "recommender",
      "text": "世界中で大人気のウィリー・ウォンカ製のチョコレート。\n彼の工場の中は完全非公開であり、謎に満ちていたのですが、生産するチョコレートの中に5枚だけ金色のチケットを同封し、それを引き当てた子供は工場を見学する権利が与えられ、さらにそのうちの一人には想像を絶する素晴らしい『賞品』がつく」という告知を出します。見事引き当てた5人の子供と保護者が、工場に入っていくのですが、その工場の中がまるでテーマパークのようで、観ているだけで甘い匂いがするほどの楽しさです。",
      "timestamp": "2023-02-13T11:07:44.585789+09:00",
      "internal_states": [
        {
          "id": "15",
          "text": "世界中",
          "knowledge": {
            "recommender": "なし",
            "seeker": "なし"
          },
          "interest": {
            "recommender": "あり",
            "seeker": "どちらとも言えない"
          }
        },
        {
          "id": "16",
          "text": "大人気のウィリー・ウォンカ製のチョコレート",
          "knowledge": {
            "recommender": "なし",
            "seeker": "なし"
          },
          "interest": {
            "recommender": "あり",
            "seeker": "あり"
          }
        },
        {
          "id": "17",
          "text": "彼の工場の中",
          "knowledge": {
            "recommender": "なし",
            "seeker": "不適切"
          },
          "interest": {
            "recommender": "あり",
            "seeker": "不適切"
          }
        },
        {
          "id": "18",
          "text": "完全非公開",
          "knowledge": {
            "recommender": "なし",
            "seeker": "あり"
          },
          "interest": {
            "recommender": "あり",
            "seeker": "あり"
          }
        },
        {
          "id": "19",
          "text": "謎",
          "knowledge": {
            "recommender": "なし",
            "seeker": "あり"
          },
          "interest": {
            "recommender": "あり",
            "seeker": "あり"
          }
        },
        {
          "id": "20",
          "text": "生産するチョコレートの中",
          "knowledge": {
            "recommender": "なし",
            "seeker": "不適切"
          },
          "interest": {
            "recommender": "どちらとも言えない",
            "seeker": "不適切"
          }
        },
        {
          "id": "21",
          "text": "5枚",
          "knowledge": {
            "recommender": "なし",
            "seeker": "あり"
          },
          "interest": {
            "recommender": "どちらとも言えない",
            "seeker": "あり"
          }
        },
        {
          "id": "22",
          "text": "金色のチケット",
          "knowledge": {
            "recommender": "なし",
            "seeker": "なし"
          },
          "interest": {
            "recommender": "どちらとも言えない",
            "seeker": "あり"
          }
        },
        {
          "id": "23",
          "text": "引き当てた子供",
          "knowledge": {
            "recommender": "なし",
            "seeker": "なし"
          },
          "interest": {
            "recommender": "どちらとも言えない",
            "seeker": "あり"
          }
        },
        {
          "id": "24",
          "text": "工場を見学する権利",
          "knowledge": {
            "recommender": "なし",
            "seeker": "あり"
          },
          "interest": {
            "recommender": "あり",
            "seeker": "あり"
          }
        },
        {
          "id": "25",
          "text": "そのうちの一人",
          "knowledge": {
            "recommender": "なし",
            "seeker": "なし"
          },
          "interest": {
            "recommender": "どちらとも言えない",
            "seeker": "あり"
          }
        },
        {
          "id": "26",
          "text": "想像",
          "knowledge": {
            "recommender": "なし",
            "seeker": "あり"
          },
          "interest": {
            "recommender": "どちらとも言えない",
            "seeker": "あり"
          }
        },
        {
          "id": "27",
          "text": "つく」という告知",
          "knowledge": {
            "recommender": "不適切",
            "seeker": "不適切"
          },
          "interest": {
            "recommender": "不適切",
            "seeker": "不適切"
          }
        },
        {
          "id": "28",
          "text": "見事",
          "knowledge": {
            "recommender": "不適切",
            "seeker": "あり"
          },
          "interest": {
            "recommender": "不適切",
            "seeker": "あり"
          }
        },
        {
          "id": "29",
          "text": "子供",
          "knowledge": {
            "recommender": "なし",
            "seeker": "あり"
          },
          "interest": {
            "recommender": "どちらとも言えない",
            "seeker": "あり"
          }
        },
        {
          "id": "30",
          "text": "保護者",
          "knowledge": {
            "recommender": "なし",
            "seeker": "あり"
          },
          "interest": {
            "recommender": "どちらとも言えない",
            "seeker": "あり"
          }
        },
        {
          "id": "31",
          "text": "工場",
          "knowledge": {
            "recommender": "なし",
            "seeker": "あり"
          },
          "interest": {
            "recommender": "あり",
            "seeker": "あり"
          }
        },
        {
          "id": "32",
          "text": "その工場の中",
          "knowledge": {
            "recommender": "なし",
            "seeker": "なし"
          },
          "interest": {
            "recommender": "あり",
            "seeker": "あり"
          }
        },
        {
          "id": "33",
          "text": "テーマパーク",
          "knowledge": {
            "recommender": "なし",
            "seeker": "あり"
          },
          "interest": {
            "recommender": "あり",
            "seeker": "あり"
          }
        },
        {
          "id": "34",
          "text": "観ているだけで甘い匂いがするほどの楽しさ",
          "knowledge": {
            "recommender": "なし",
            "seeker": "なし"
          },
          "interest": {
            "recommender": "あり",
            "seeker": "あり"
          }
        }
      ],
      "searches": [],
      "checked": [
        "321598_plot-0",
        "321598_plot-1",
        "321598_plot-2"
      ]
    },
    {
      "id": "9",
      "speaker": "seeker",
      "text": "工場見学したくなる映画ですね。いろんな仕掛けがあるのかしら。",
      "timestamp": "2023-02-13T11:08:34.692905+09:00",
      "internal_states": [
        {
          "id": "35",
          "text": "工場見学したくなる映画",
          "knowledge": {
            "recommender": "なし",
            "seeker": "なし"
          },
          "interest": {
            "recommender": "あり",
            "seeker": "あり"
          }
        },
        {
          "id": "36",
          "text": "いろんな仕掛け",
          "knowledge": {
            "recommender": "なし",
            "seeker": "どちらとも言えない"
          },
          "interest": {
            "recommender": "あり",
            "seeker": "あり"
          }
        }
      ]
    },
    {
      "id": "10",
      "speaker": "recommender",
      "text": "工場の中で夢のように不思議な体験していく子供たちですが、途中でさまざまなハプニングが起こり、一人ずつ脱落していきます。最後に残ったチャーリーに『賞品』を与える交換条件として提示されたものは「家族を捨てること」という受け入れがたいものだったため、チャーリーはこれを辞退するのです。",
      "timestamp": "2023-02-13T11:09:58.074811+09:00",
      "internal_states": [
        {
          "id": "37",
          "text": "工場の中",
          "knowledge": {
            "recommender": "なし",
            "seeker": "なし"
          },
          "interest": {
            "recommender": "あり",
            "seeker": "あり"
          }
        },
        {
          "id": "38",
          "text": "夢のように不思議な体験していく子供たち",
          "knowledge": {
            "recommender": "なし",
            "seeker": "なし"
          },
          "interest": {
            "recommender": "あり",
            "seeker": "あり"
          }
        },
        {
          "id": "39",
          "text": "途中",
          "knowledge": {
            "recommender": "なし",
            "seeker": "あり"
          },
          "interest": {
            "recommender": "あり",
            "seeker": "あり"
          }
        },
        {
          "id": "40",
          "text": "さまざまなハプニング",
          "knowledge": {
            "recommender": "なし",
            "seeker": "なし"
          },
          "interest": {
            "recommender": "あり",
            "seeker": "あり"
          }
        },
        {
          "id": "41",
          "text": "一人ずつ",
          "knowledge": {
            "recommender": "なし",
            "seeker": "不適切"
          },
          "interest": {
            "recommender": "あり",
            "seeker": "不適切"
          }
        },
        {
          "id": "42",
          "text": "最後に残ったチャーリーに『賞品』を与える交換条件として提示されたもの",
          "knowledge": {
            "recommender": "なし",
            "seeker": "不適切"
          },
          "interest": {
            "recommender": "あり",
            "seeker": "不適切"
          }
        },
        {
          "id": "43",
          "text": "「家族を捨てること」という受け入れがたいものだったため",
          "knowledge": {
            "recommender": "なし",
            "seeker": "不適切"
          },
          "interest": {
            "recommender": "あり",
            "seeker": "不適切"
          }
        },
        {
          "id": "44",
          "text": "チャーリー",
          "knowledge": {
            "recommender": "なし",
            "seeker": "なし"
          },
          "interest": {
            "recommender": "どちらとも言えない",
            "seeker": "あり"
          }
        }
      ],
      "searches": [],
      "checked": [
        "321598_plot-5",
        "321598_plot-6"
      ]
    },
    {
      "id": "11",
      "speaker": "seeker",
      "text": "楽しいだけの映画ではないのですね。でも、どんな映像なのかしらと見たくなりました。衣装や音楽は楽しめそうですか。",
      "timestamp": "2023-02-13T11:11:16.610737+09:00",
      "internal_states": [
        {
          "id": "45",
          "text": "楽しいだけの映画",
          "knowledge": {
            "recommender": "なし",
            "seeker": "どちらとも言えない"
          },
          "interest": {
            "recommender": "あり",
            "seeker": "どちらとも言えない"
          }
        },
        {
          "id": "46",
          "text": "どんな映像",
          "knowledge": {
            "recommender": "なし",
            "seeker": "不適切"
          },
          "interest": {
            "recommender": "あり",
            "seeker": "不適切"
          }
        },
        {
          "id": "47",
          "text": "衣装や音楽",
          "knowledge": {
            "recommender": "なし",
            "seeker": "あり"
          },
          "interest": {
            "recommender": "あり",
            "seeker": "あり"
          }
        }
      ]
    },
    {
      "id": "12",
      "speaker": "recommender",
      "text": "ジョニーのメイクも髪型もすごく、個性的というか、変ですが、憎めないキャラクターをとても上手に演じられています。工場の中に、小人が住んでいて、彼らがチョコレートを作っているところの音楽と、踊りがとても面白くて何度も見てしまいます。",
      "timestamp": "2023-02-13T11:12:19.870276+09:00",
      "internal_states": [
        {
          "id": "48",
          "text": "メイク",
          "knowledge": {
            "recommender": "なし",
            "seeker": "どちらとも言えない"
          },
          "interest": {
            "recommender": "あり",
            "seeker": "あり"
          }
        },
        {
          "id": "49",
          "text": "髪型",
          "knowledge": {
            "recommender": "なし",
            "seeker": "どちらとも言えない"
          },
          "interest": {
            "recommender": "あり",
            "seeker": "あり"
          }
        },
        {
          "id": "50",
          "text": "個性",
          "knowledge": {
            "recommender": "なし",
            "seeker": "あり"
          },
          "interest": {
            "recommender": "あり",
            "seeker": "あり"
          }
        },
        {
          "id": "51",
          "text": "憎めないキャラクター",
          "knowledge": {
            "recommender": "なし",
            "seeker": "あり"
          },
          "interest": {
            "recommender": "あり",
            "seeker": "あり"
          }
        },
        {
          "id": "52",
          "text": "工場の中",
          "knowledge": {
            "recommender": "なし",
            "seeker": "不適切"
          },
          "interest": {
            "recommender": "あり",
            "seeker": "不適切"
          }
        },
        {
          "id": "53",
          "text": "小人",
          "knowledge": {
            "recommender": "なし",
            "seeker": "あり"
          },
          "interest": {
            "recommender": "どちらとも言えない",
            "seeker": "あり"
          }
        },
        {
          "id": "54",
          "text": "彼ら",
          "knowledge": {
            "recommender": "なし",
            "seeker": "なし"
          },
          "interest": {
            "recommender": "どちらとも言えない",
            "seeker": "あり"
          }
        },
        {
          "id": "55",
          "text": "チョコレートを作っているところ",
          "knowledge": {
            "recommender": "なし",
            "seeker": "あり"
          },
          "interest": {
            "recommender": "あり",
            "seeker": "あり"
          }
        },
        {
          "id": "56",
          "text": "音楽",
          "knowledge": {
            "recommender": "なし",
            "seeker": "あり"
          },
          "interest": {
            "recommender": "あり",
            "seeker": "あり"
          }
        },
        {
          "id": "57",
          "text": "踊り",
          "knowledge": {
            "recommender": "なし",
            "seeker": "あり"
          },
          "interest": {
            "recommender": "あり",
            "seeker": "あり"
          }
        }
      ],
      "searches": [],
      "checked": [
        "321598_plot-7"
      ]
    },
    {
      "id": "13",
      "speaker": "seeker",
      "text": "わあ、ほんとに面白そうな映画ですね。何か童話を元にしたお話のような感じがしますが・・",
      "timestamp": "2023-02-13T11:13:38.154184+09:00",
      "internal_states": [
        {
          "id": "58",
          "text": "わあ、ほんとに面白そうな映画",
          "knowledge": {
            "recommender": "不適切",
            "seeker": "不適切"
          },
          "interest": {
            "recommender": "不適切",
            "seeker": "不適切"
          }
        },
        {
          "id": "59",
          "text": "何か童話を元にしたお話のような感じ",
          "knowledge": {
            "recommender": "なし",
            "seeker": "不適切"
          },
          "interest": {
            "recommender": "あり",
            "seeker": "不適切"
          }
        }
      ]
    },
    {
      "id": "14",
      "speaker": "recommender",
      "text": "確か、もともとオリジナルの映画か、絵本があったかと思います。そういえば、先ほど提示させて頂いた、もう一つの映画「ショコラ」もジョニー・デップが出ているのを今思い出しました。シリアスな役柄なのでぜんぜんイメージが変わりますが、二つを比較してバレンタインをお楽しみいただくのもアリかもしれませんね。",
      "timestamp": "2023-02-13T11:14:25.060506+09:00",
      "internal_states": [
        {
          "id": "60",
          "text": "オリジナルの映画",
          "knowledge": {
            "recommender": "なし",
            "seeker": "あり"
          },
          "interest": {
            "recommender": "どちらとも言えない",
            "seeker": "あり"
          }
        },
        {
          "id": "61",
          "text": "絵本",
          "knowledge": {
            "recommender": "なし",
            "seeker": "あり"
          },
          "interest": {
            "recommender": "あり",
            "seeker": "あり"
          }
        },
        {
          "id": "62",
          "text": "先ほど",
          "knowledge": {
            "recommender": "不適切",
            "seeker": "不適切"
          },
          "interest": {
            "recommender": "不適切",
            "seeker": "不適切"
          }
        },
        {
          "id": "63",
          "text": "一つの映画",
          "knowledge": {
            "recommender": "不適切",
            "seeker": "あり"
          },
          "interest": {
            "recommender": "不適切",
            "seeker": "あり"
          }
        },
        {
          "id": "64",
          "text": "「ショコラ」",
          "knowledge": {
            "recommender": "不適切",
            "seeker": "なし"
          },
          "interest": {
            "recommender": "不適切",
            "seeker": "あり"
          }
        },
        {
          "id": "65",
          "text": "ジョニー・デップ",
          "knowledge": {
            "recommender": "あり",
            "seeker": "あり"
          },
          "interest": {
            "recommender": "あり",
            "seeker": "あり"
          }
        },
        {
          "id": "66",
          "text": "シリアスな役柄",
          "knowledge": {
            "recommender": "なし",
            "seeker": "あり"
          },
          "interest": {
            "recommender": "どちらとも言えない",
            "seeker": "あり"
          }
        },
        {
          "id": "67",
          "text": "イメージ",
          "knowledge": {
            "recommender": "なし",
            "seeker": "あり"
          },
          "interest": {
            "recommender": "どちらとも言えない",
            "seeker": "あり"
          }
        },
        {
          "id": "68",
          "text": "二つ",
          "knowledge": {
            "recommender": "不適切",
            "seeker": "不適切"
          },
          "interest": {
            "recommender": "不適切",
            "seeker": "不適切"
          }
        },
        {
          "id": "69",
          "text": "バレンタイン",
          "knowledge": {
            "recommender": "不適切",
            "seeker": "あり"
          },
          "interest": {
            "recommender": "不適切",
            "seeker": "あり"
          }
        },
        {
          "id": "70",
          "text": "アリ",
          "knowledge": {
            "recommender": "不適切",
            "seeker": "不適切"
          },
          "interest": {
            "recommender": "不適切",
            "seeker": "不適切"
          }
        }
      ],
      "searches": [],
      "checked": []
    },
    {
      "id": "15",
      "speaker": "seeker",
      "text": "彼の映画は良い作品が多いですね。",
      "timestamp": "2023-02-13T11:15:14.065523+09:00",
      "internal_states": [
        {
          "id": "71",
          "text": "彼の映画",
          "knowledge": {
            "recommender": "あり",
            "seeker": "あり"
          },
          "interest": {
            "recommender": "あり",
            "seeker": "あり"
          }
        },
        {
          "id": "72",
          "text": "良い作品",
          "knowledge": {
            "recommender": "あり",
            "seeker": "あり"
          },
          "interest": {
            "recommender": "あり",
            "seeker": "あり"
          }
        }
      ]
    },
    {
      "id": "16",
      "speaker": "recommender",
      "text": "色々な役柄ができる俳優さんですね。今日はお付き合いありがとうございました。良いバレンタインをお迎えください。",
      "timestamp": "2023-02-13T11:15:37.598144+09:00",
      "internal_states": [
        {
          "id": "73",
          "text": "色々な役柄",
          "knowledge": {
            "recommender": "どちらとも言えない",
            "seeker": "どちらとも言えない"
          },
          "interest": {
            "recommender": "どちらとも言えない",
            "seeker": "あり"
          }
        },
        {
          "id": "74",
          "text": "できる俳優さん",
          "knowledge": {
            "recommender": "どちらとも言えない",
            "seeker": "不適切"
          },
          "interest": {
            "recommender": "どちらとも言えない",
            "seeker": "不適切"
          }
        },
        {
          "id": "75",
          "text": "良いバレンタイン",
          "knowledge": {
            "recommender": "不適切",
            "seeker": "不適切"
          },
          "interest": {
            "recommender": "不適切",
            "seeker": "不適切"
          }
        }
      ],
      "searches": [],
      "checked": []
    },
    {
      "id": "17",
      "speaker": "seeker",
      "text": "いい作品をお勧めいただき、有り難うございました。",
      "timestamp": "2023-02-13T11:16:04.139536+09:00",
      "internal_states": [
        {
          "id": "76",
          "text": "いい作品",
          "knowledge": {
            "recommender": "なし",
            "seeker": "あり"
          },
          "interest": {
            "recommender": "あり",
            "seeker": "あり"
          }
        }
      ]
    }
  ]
}