{
  "dialog_id": "5a50b291-7b72-4551-a5c6-4c06fd55e258",
  "created_timestamp": "2023-01-30T21:29:16.229353+09:00",
  "archived_timestamp": "2023-01-30T21:54:12.316370+09:00",
  "recommender": {
    "name": "041",
    "questionnaire": {
      "knowledge": 5,
      "enjoyment": 5,
      "recommendation_success": 5,
      "movie_num": 5
    }
  },
  "seeker": {
    "name": "034",
    "questionnaire": {
      "knowledge": 3,
      "enjoyment": 5,
      "recommendation_success": 5,
      "movie_num": 4
    }
  },
  "utterances": [
    {
      "id": "0",
      "speaker": "recommender",
      "text": "こんばんは！よろしくお願いします。",
      "timestamp": "2023-01-30T21:37:16.246547+09:00",
      "internal_states": [],
      "searches": [],
      "checked": []
    },
    {
      "id": "1",
      "speaker": "seeker",
      "text": "こんばんわ。宜しくお願いします。",
      "timestamp": "2023-01-30T21:37:21.548542+09:00",
      "internal_states": []
    },
    {
      "id": "2",
      "speaker": "recommender",
      "text": "どんな映画がお好きですか？",
      "timestamp": "2023-01-30T21:37:31.625155+09:00",
      "internal_states": [],
      "searches": [],
      "checked": []
    },
    {
      "id": "3",
      "speaker": "seeker",
      "text": "元気の出るような映画が好きです。",
      "timestamp": "2023-01-30T21:37:49.242979+09:00",
      "internal_states": [
        {
          "id": "0",
          "text": "元気の出るような映画",
          "knowledge": {
            "recommender": "どちらとも言えない",
            "seeker": "あり"
          },
          "interest": {
            "recommender": "あり",
            "seeker": "あり"
          }
        }
      ]
    },
    {
      "id": "4",
      "speaker": "recommender",
      "text": "「キューティ・ブロンド」はご覧になりました？　もう二十年前の映画になるのですが、これが出た時にさらに古い「ワーキング・ガール」のカレッジ版だーと思ったのを覚えています。",
      "timestamp": "2023-01-30T21:39:32.292277+09:00",
      "internal_states": [
        {
          "id": "1",
          "text": "「キューティ・ブロンド」",
          "knowledge": {
            "recommender": "なし",
            "seeker": "あり"
          },
          "interest": {
            "recommender": "あり",
            "seeker": "なし"
          }
        },
        {
          "id": "2",
          "text": "二十年前の映画",
          "knowledge": {
            "recommender": "不適切",
            "seeker": "あり"
          },
          "interest": {
            "recommender": "不適切",
            "seeker": "あり"
          }
        },
        {
          "id": "3",
          "text": "これが出た時",
          "knowledge": {
            "recommender": "不適切",
            "seeker": "不適切"
          },
          "interest": {
            "recommender": "不適切",
            "seeker": "不適切"
          }
        },
        {
          "id": "4",
          "text": "古い「ワーキング・ガール」のカレッジ版",
          "knowledge": {
            "recommender": "どちらとも言えない",
            "seeker": "どちらとも言えない"
          },
          "interest": {
            "recommender": "どちらとも言えない",
            "seeker": "あり"
          }
        }
      ],
      "searches": [
        {
          "timestamp": "2023-01-30T21:38:03.708949+09:00",
          "query": "キューティー",
          "genres": "",
          "results": ""
        },
        {
          "timestamp": "2023-01-30T21:38:10.406229+09:00",
          "query": "ブロンド",
          "genres": "",
          "results": "1281,236645,361036"
        }
      ],
      "checked": []
    },
    {
      "id": "5",
      "speaker": "seeker",
      "text": "ワーキングガールはみたことありますがキューティ・ブロンドないです！",
      "timestamp": "2023-01-30T21:40:10.440992+09:00",
      "internal_states": [
        {
          "id": "5",
          "text": "ワーキングガール",
          "knowledge": {
            "recommender": "あり",
            "seeker": "あり"
          },
          "interest": {
            "recommender": "あり",
            "seeker": "あり"
          }
        },
        {
          "id": "6",
          "text": "みたこと",
          "knowledge": {
            "recommender": "不適切",
            "seeker": "不適切"
          },
          "interest": {
            "recommender": "不適切",
            "seeker": "不適切"
          }
        },
        {
          "id": "7",
          "text": "キューティ・ブロンド",
          "knowledge": {
            "recommender": "なし",
            "seeker": "あり"
          },
          "interest": {
            "recommender": "あり",
            "seeker": "あり"
          }
        }
      ]
    },
    {
      "id": "6",
      "speaker": "recommender",
      "text": "おおっ！ワーキングガールをご存じとは嬉しいです！「キューティ・ブロンド」もちょっと成り上がりを頑張る女の子の話、ばかばかしく笑える上に思いっきり元気が出るが出る映画なのでお薦めです。",
      "timestamp": "2023-01-30T21:42:09.138968+09:00",
      "internal_states": [
        {
          "id": "8",
          "text": "ワーキングガール",
          "knowledge": {
            "recommender": "あり",
            "seeker": "あり"
          },
          "interest": {
            "recommender": "あり",
            "seeker": "あり"
          }
        },
        {
          "id": "9",
          "text": "「キューティ・ブロンド」",
          "knowledge": {
            "recommender": "なし",
            "seeker": "あり"
          },
          "interest": {
            "recommender": "あり",
            "seeker": "どちらとも言えない"
          }
        },
        {
          "id": "10",
          "text": "成り上がりを頑張る女の子の話、ばかばかしく笑える上",
          "knowledge": {
            "recommender": "不適切",
            "seeker": "あり"
          },
          "interest": {
            "recommender": "不適切",
            "seeker": "あり"
          }
        },
        {
          "id": "11",
          "text": "元気が出るが出る映画",
          "knowledge": {
            "recommender": "あり",
            "seeker": "不適切"
          },
          "interest": {
            "recommender": "あり",
            "seeker": "不適切"
          }
        }
      ],
      "searches": [
        {
          "timestamp": "2023-01-30T21:39:38.332263+09:00",
          "query": "ワーキング・ガール",
          "genres": "",
          "results": ""
        },
        {
          "timestamp": "2023-01-30T21:39:47.079586+09:00",
          "query": "ブロンド",
          "genres": "",
          "results": "1281,236645,361036"
        }
      ],
      "checked": [
        "236645_title"
      ]
    },
    {
      "id": "7",
      "speaker": "seeker",
      "text": "アメリカ!って感じの映画っぽいですよね",
      "timestamp": "2023-01-30T21:42:44.588161+09:00",
      "internal_states": [
        {
          "id": "12",
          "text": "アメリカ",
          "knowledge": {
            "recommender": "あり",
            "seeker": "あり"
          },
          "interest": {
            "recommender": "あり",
            "seeker": "あり"
          }
        }
      ]
    },
    {
      "id": "8",
      "speaker": "recommender",
      "text": "そうなのです！ピンクばっかり着るおしゃれにしか興味のない女の子が彼氏を取り戻すべくハーバード（？）で弁護士目指すというど根性ものです。",
      "timestamp": "2023-01-30T21:43:57.557561+09:00",
      "internal_states": [
        {
          "id": "13",
          "text": "ピンクばっかり着るおしゃれにしか興味のない女の子",
          "knowledge": {
            "recommender": "どちらとも言えない",
            "seeker": "あり"
          },
          "interest": {
            "recommender": "どちらとも言えない",
            "seeker": "なし"
          }
        },
        {
          "id": "14",
          "text": "彼氏",
          "knowledge": {
            "recommender": "不適切",
            "seeker": "不適切"
          },
          "interest": {
            "recommender": "不適切",
            "seeker": "不適切"
          }
        },
        {
          "id": "15",
          "text": "ハーバード",
          "knowledge": {
            "recommender": "あり",
            "seeker": "どちらとも言えない"
          },
          "interest": {
            "recommender": "あり",
            "seeker": "どちらとも言えない"
          }
        },
        {
          "id": "16",
          "text": "弁護士目指すというど根性もの",
          "knowledge": {
            "recommender": "不適切",
            "seeker": "あり"
          },
          "interest": {
            "recommender": "不適切",
            "seeker": "あり"
          }
        }
      ],
      "searches": [],
      "checked": []
    },
    {
      "id": "9",
      "speaker": "seeker",
      "text": "確か２とかもありましたよね？タイトルだけ見てみる気がしなかったのですが(笑）、それは面白そうですね。",
      "timestamp": "2023-01-30T21:44:43.706082+09:00",
      "internal_states": [
        {
          "id": "17",
          "text": "２",
          "knowledge": {
            "recommender": "不適切",
            "seeker": "不適切"
          },
          "interest": {
            "recommender": "不適切",
            "seeker": "不適切"
          }
        },
        {
          "id": "18",
          "text": "タイトルだけ見てみる気",
          "knowledge": {
            "recommender": "不適切",
            "seeker": "不適切"
          },
          "interest": {
            "recommender": "不適切",
            "seeker": "不適切"
          }
        }
      ]
    },
    {
      "id": "10",
      "speaker": "recommender",
      "text": "あったあった！でも最初の方がいいですよ！何しろ、おしゃれ一徹の彼女は馬鹿なんかじゃなく、ちゃんと論理的に戦えるし、他の負け組チックなキャラもみんなハッピーになるのですよ、最後に。",
      "timestamp": "2023-01-30T21:46:22.552109+09:00",
      "internal_states": [
        {
          "id": "19",
          "text": "あったあった！でも最初の方",
          "knowledge": {
            "recommender": "不適切",
            "seeker": "不適切"
          },
          "interest": {
            "recommender": "不適切",
            "seeker": "不適切"
          }
        },
        {
          "id": "20",
          "text": "おしゃれ一徹の彼女",
          "knowledge": {
            "recommender": "なし",
            "seeker": "あり"
          },
          "interest": {
            "recommender": "どちらとも言えない",
            "seeker": "あり"
          }
        },
        {
          "id": "21",
          "text": "馬鹿",
          "knowledge": {
            "recommender": "不適切",
            "seeker": "不適切"
          },
          "interest": {
            "recommender": "不適切",
            "seeker": "不適切"
          }
        },
        {
          "id": "22",
          "text": "他の負け組チックなキャラ",
          "knowledge": {
            "recommender": "不適切",
            "seeker": "あり"
          },
          "interest": {
            "recommender": "不適切",
            "seeker": "あり"
          }
        }
      ],
      "searches": [],
      "checked": []
    },
    {
      "id": "11",
      "speaker": "seeker",
      "text": "女性が口で相手を圧倒するのってスカッとしますよね！！最後ハッピーで終わるのも良いです。",
      "timestamp": "2023-01-30T21:48:05.465528+09:00",
      "internal_states": [
        {
          "id": "23",
          "text": "女性",
          "knowledge": {
            "recommender": "あり",
            "seeker": "あり"
          },
          "interest": {
            "recommender": "どちらとも言えない",
            "seeker": "あり"
          }
        },
        {
          "id": "24",
          "text": "口",
          "knowledge": {
            "recommender": "不適切",
            "seeker": "不適切"
          },
          "interest": {
            "recommender": "不適切",
            "seeker": "不適切"
          }
        },
        {
          "id": "25",
          "text": "相手",
          "knowledge": {
            "recommender": "不適切",
            "seeker": "不適切"
          },
          "interest": {
            "recommender": "不適切",
            "seeker": "不適切"
          }
        },
        {
          "id": "26",
          "text": "スカッ",
          "knowledge": {
            "recommender": "不適切",
            "seeker": "不適切"
          },
          "interest": {
            "recommender": "不適切",
            "seeker": "不適切"
          }
        },
        {
          "id": "27",
          "text": "最後",
          "knowledge": {
            "recommender": "不適切",
            "seeker": "不適切"
          },
          "interest": {
            "recommender": "不適切",
            "seeker": "不適切"
          }
        }
      ]
    },
    {
      "id": "12",
      "speaker": "recommender",
      "text": "爽快感はワーキング・ガールより高いのです！個人的にワーキング・ガールは90年代に元気を出すために見た映画、今世紀なら「キューティ・ブロンド」だと思っています。",
      "timestamp": "2023-01-30T21:48:27.648288+09:00",
      "internal_states": [
        {
          "id": "28",
          "text": "爽快感",
          "knowledge": {
            "recommender": "どちらとも言えない",
            "seeker": "あり"
          },
          "interest": {
            "recommender": "あり",
            "seeker": "あり"
          }
        },
        {
          "id": "29",
          "text": "ワーキング・ガール",
          "knowledge": {
            "recommender": "あり",
            "seeker": "あり"
          },
          "interest": {
            "recommender": "あり",
            "seeker": "あり"
          }
        },
        {
          "id": "30",
          "text": "90年代に元気を出すために見た映画、今世紀",
          "knowledge": {
            "recommender": "不適切",
            "seeker": "不適切"
          },
          "interest": {
            "recommender": "不適切",
            "seeker": "不適切"
          }
        },
        {
          "id": "31",
          "text": "「キューティ・ブロンド」",
          "knowledge": {
            "recommender": "なし",
            "seeker": "あり"
          },
          "interest": {
            "recommender": "あり",
            "seeker": "あり"
          }
        }
      ],
      "searches": [],
      "checked": []
    },
    {
      "id": "13",
      "speaker": "seeker",
      "text": "それはちょっと見てみたいですね。ワーキングガールも主人公が恰好良くて好きでした",
      "timestamp": "2023-01-30T21:49:24.576478+09:00",
      "internal_states": [
        {
          "id": "32",
          "text": "ワーキングガール",
          "knowledge": {
            "recommender": "あり",
            "seeker": "あり"
          },
          "interest": {
            "recommender": "あり",
            "seeker": "あり"
          }
        },
        {
          "id": "33",
          "text": "主人公",
          "knowledge": {
            "recommender": "不適切",
            "seeker": "あり"
          },
          "interest": {
            "recommender": "不適切",
            "seeker": "あり"
          }
        }
      ]
    },
    {
      "id": "14",
      "speaker": "recommender",
      "text": "そうですよね！　でもワーキングガールは相手が女の上司、「キューティ・ブロンド」は男相手に任すのでより爽快感が高いのかも。",
      "timestamp": "2023-01-30T21:50:34.250625+09:00",
      "internal_states": [
        {
          "id": "34",
          "text": "ワーキングガール",
          "knowledge": {
            "recommender": "あり",
            "seeker": "あり"
          },
          "interest": {
            "recommender": "あり",
            "seeker": "あり"
          }
        },
        {
          "id": "35",
          "text": "相手",
          "knowledge": {
            "recommender": "不適切",
            "seeker": "どちらとも言えない"
          },
          "interest": {
            "recommender": "不適切",
            "seeker": "どちらとも言えない"
          }
        },
        {
          "id": "36",
          "text": "女の上司",
          "knowledge": {
            "recommender": "どちらとも言えない",
            "seeker": "あり"
          },
          "interest": {
            "recommender": "どちらとも言えない",
            "seeker": "どちらとも言えない"
          }
        },
        {
          "id": "37",
          "text": "「キューティ・ブロンド」",
          "knowledge": {
            "recommender": "なし",
            "seeker": "あり"
          },
          "interest": {
            "recommender": "あり",
            "seeker": "あり"
          }
        },
        {
          "id": "38",
          "text": "男相手",
          "knowledge": {
            "recommender": "不適切",
            "seeker": "どちらとも言えない"
          },
          "interest": {
            "recommender": "不適切",
            "seeker": "どちらとも言えない"
          }
        },
        {
          "id": "39",
          "text": "爽快感",
          "knowledge": {
            "recommender": "あり",
            "seeker": "あり"
          },
          "interest": {
            "recommender": "あり",
            "seeker": "あり"
          }
        }
      ],
      "searches": [],
      "checked": []
    },
    {
      "id": "15",
      "speaker": "seeker",
      "text": "なるほど、そういうことですね。",
      "timestamp": "2023-01-30T21:50:49.008045+09:00",
      "internal_states": [
        {
          "id": "40",
          "text": "そういうこと",
          "knowledge": {
            "recommender": "不適切",
            "seeker": "不適切"
          },
          "interest": {
            "recommender": "不適切",
            "seeker": "不適切"
          }
        }
      ]
    },
    {
      "id": "16",
      "speaker": "recommender",
      "text": "そうなんですよ！おしゃれや美容の知識をフル回転して事件を解決に持ち込むのです。これがちゃんと筋が通っていて◎",
      "timestamp": "2023-01-30T21:52:00.328093+09:00",
      "internal_states": [
        {
          "id": "41",
          "text": "おしゃれや美容の知識",
          "knowledge": {
            "recommender": "あり",
            "seeker": "あり"
          },
          "interest": {
            "recommender": "どちらとも言えない",
            "seeker": "あり"
          }
        },
        {
          "id": "42",
          "text": "フル",
          "knowledge": {
            "recommender": "不適切",
            "seeker": "不適切"
          },
          "interest": {
            "recommender": "不適切",
            "seeker": "どちらとも言えない"
          }
        },
        {
          "id": "43",
          "text": "事件",
          "knowledge": {
            "recommender": "不適切",
            "seeker": "あり"
          },
          "interest": {
            "recommender": "不適切",
            "seeker": "あり"
          }
        },
        {
          "id": "44",
          "text": "解決",
          "knowledge": {
            "recommender": "不適切",
            "seeker": "あり"
          },
          "interest": {
            "recommender": "不適切",
            "seeker": "あり"
          }
        },
        {
          "id": "45",
          "text": "筋",
          "knowledge": {
            "recommender": "不適切",
            "seeker": "あり"
          },
          "interest": {
            "recommender": "不適切",
            "seeker": "あり"
          }
        }
      ],
      "searches": [],
      "checked": []
    },
    {
      "id": "17",
      "speaker": "seeker",
      "text": "女の武器もちゃんと使うんですね。好みかもです（笑）今度見てみたいと思います！",
      "timestamp": "2023-01-30T21:52:49.665135+09:00",
      "internal_states": [
        {
          "id": "46",
          "text": "女の武器",
          "knowledge": {
            "recommender": "あり",
            "seeker": "あり"
          },
          "interest": {
            "recommender": "どちらとも言えない",
            "seeker": "あり"
          }
        },
        {
          "id": "47",
          "text": "好みかもです（笑）今度",
          "knowledge": {
            "recommender": "不適切",
            "seeker": "不適切"
          },
          "interest": {
            "recommender": "不適切",
            "seeker": "不適切"
          }
        }
      ]
    },
    {
      "id": "18",
      "speaker": "recommender",
      "text": "ぜひぜひ見てください。めちゃ元気に温かくなれる映画です！",
      "timestamp": "2023-01-30T21:53:22.272479+09:00",
      "internal_states": [
        {
          "id": "48",
          "text": "めちゃ元気に温かくなれる映画",
          "knowledge": {
            "recommender": "どちらとも言えない",
            "seeker": "あり"
          },
          "interest": {
            "recommender": "どちらとも言えない",
            "seeker": "あり"
          }
        }
      ],
      "searches": [],
      "checked": []
    },
    {
      "id": "19",
      "speaker": "seeker",
      "text": "分かりました！おすすめ有り難うございますー",
      "timestamp": "2023-01-30T21:53:47.705873+09:00",
      "internal_states": []
    },
    {
      "id": "20",
      "speaker": "recommender",
      "text": "ありがとうございました！",
      "timestamp": "2023-01-30T21:54:01.213029+09:00",
      "internal_states": [],
      "searches": [],
      "checked": []
    }
  ]
}